odoo/addons/stock_account_valuation_discrepancy_adjust/README.rst
odoo/addons/stock_account_valuation_discrepancy_adjust/__init__.py
odoo/addons/stock_account_valuation_discrepancy_adjust/__manifest__.py
odoo/addons/stock_account_valuation_discrepancy_adjust/i18n/it.po
odoo/addons/stock_account_valuation_discrepancy_adjust/i18n/stock_account_valuation_discrepancy_adjust.pot
odoo/addons/stock_account_valuation_discrepancy_adjust/readme/CONTRIBUTORS.rst
odoo/addons/stock_account_valuation_discrepancy_adjust/readme/DESCRIPTION.rst
odoo/addons/stock_account_valuation_discrepancy_adjust/security/ir.model.access.csv
odoo/addons/stock_account_valuation_discrepancy_adjust/static/description/icon.png
odoo/addons/stock_account_valuation_discrepancy_adjust/static/description/index.html
odoo/addons/stock_account_valuation_discrepancy_adjust/tests/__init__.py
odoo/addons/stock_account_valuation_discrepancy_adjust/tests/test_stock_account_valuation_discrepancy_adjust.py
odoo/addons/stock_account_valuation_discrepancy_adjust/views/product_discrepancy_view.xml
odoo/addons/stock_account_valuation_discrepancy_adjust/wizards/__init__.py
odoo/addons/stock_account_valuation_discrepancy_adjust/wizards/wizard_stock_discrepancy_adjustment.py
odoo/addons/stock_account_valuation_discrepancy_adjust/wizards/wizard_stock_discrepancy_adjustment_view.xml
odoo_addon_stock_account_valuation_discrepancy_adjust-16.0.1.0.0.6.dist-info/METADATA
odoo_addon_stock_account_valuation_discrepancy_adjust-16.0.1.0.0.6.dist-info/WHEEL
odoo_addon_stock_account_valuation_discrepancy_adjust-16.0.1.0.0.6.dist-info/top_level.txt
odoo_addon_stock_account_valuation_discrepancy_adjust-16.0.1.0.0.6.dist-info/RECORD
