Metadata-Version: 2.1
Name: odoo-addon-stock_account_valuation_discrepancy_adjust
Version: 16.0.1.0.0.6
Summary: Implements Wizard for Adjust Discrepancies on Account Inventory Valuation
Home-page: https://github.com/OCA/stock-logistics-reporting
Author: ForgeFlow, Odoo Community Association (OCA)
Author-email: support@odoo-community.org
License: AGPL-3
Classifier: Programming Language :: Python
Classifier: Framework :: Odoo
Classifier: Framework :: Odoo :: 16.0
Classifier: License :: OSI Approved :: GNU Affero General Public License v3
Classifier: Development Status :: 3 - Alpha
Requires-Python: >=3.10
Requires-Dist: odoo-addon-stock-account-valuation-report<16.1dev,>=16.0dev
Requires-Dist: odoo<16.1dev,>=16.0a
